websub/__init__.py
websub-0.1.3.dist-info/LICENCE
websub-0.1.3.dist-info/METADATA
websub-0.1.3.dist-info/WHEEL
websub-0.1.3.dist-info/top_level.txt
websub-0.1.3.dist-info/RECORD
