Metadata-Version: 2.1
Name: websub
Version: 0.1.3
Summary: WebSub Client for python, based off of gohubbub
Home-page: https://github.com/ShadowJonathan/pywebsub
Author: Jonathan de Jong
Author-email: jonathan@automatia.nl
License: UNKNOWN
Platform: UNKNOWN
Classifier: Programming Language :: Python :: 3
Classifier: License :: OSI Approved :: MIT License
Classifier: Operating System :: OS Independent
Requires-Dist: sanic
Requires-Dist: httpx
Requires-Dist: anyio
Requires-Dist: bs4
Requires-Dist: lxml
Provides-Extra: dev
Requires-Dist: ipython ; extra == 'dev'
Requires-Dist: twine ; extra == 'dev'
